classmail/__init__.py
classmail/classification/__init__.py
classmail/classification/model.py
classmail/classification/trainer.py
classmail/data_visualisation/__init__.py
classmail/data_visualisation/data_visualisation.py
classmail/nlp/__init__.py
classmail/nlp/cleaning.py
classmail/nlp/conf.json
classmail/nlp/configjson.py
classmail/nlp/df_multiprocessing.py
classmail/nlp/get_only_messages.py
classmail-0.1.data/data/config/conf.json
classmail-0.1.dist-info/LICENSE
classmail-0.1.dist-info/METADATA
classmail-0.1.dist-info/WHEEL
classmail-0.1.dist-info/top_level.txt
classmail-0.1.dist-info/RECORD
