Metadata-Version: 2.1
Name: classmail
Version: 0.1
Summary: A simple framework for automatise mail classification task
Home-page: https://github.com/Fabien-Couthouis/ClassMail
Author: Fabien Couthouis
Author-email: fcouthouis@ensc.fr
License: MIT
Platform: UNKNOWN
Requires-Python: >=3.6
Requires-Dist: Unidecode (>=1.0.23)
Requires-Dist: flair (>=0.4.3)
Requires-Dist: joblib (>=0.13.2)
Requires-Dist: lime (>=0.1.1.36)
Requires-Dist: matplotlib (>=3.1.0)
Requires-Dist: numpy (>=1.16.3)
Requires-Dist: pandas (>=0.24.2)
Requires-Dist: seaborn (>=0.9.0)
Requires-Dist: sklearn (>=0.0)
Requires-Dist: torch (>=1.1.0)
Requires-Dist: tqdm (>=4.31.1)
Requires-Dist: wordcloud (>=1.5.0)
